atla_insights/__init__.py
atla_insights/console_span_exporter.py
atla_insights/constants.py
atla_insights/context.py
atla_insights/custom_metrics.py
atla_insights/environment.py
atla_insights/experiments.py
atla_insights/git_info.py
atla_insights/id_generator.py
atla_insights/instrument.py
atla_insights/main.py
atla_insights/marking.py
atla_insights/metadata.py
atla_insights/sampling.py
atla_insights/span.py
atla_insights/span_processors.py
atla_insights/suppression.py
atla_insights/tool.py
atla_insights/utils.py
atla_insights/client/.openapi-generator-ignore
atla_insights/client/__init__.py
atla_insights/client/_generated_client_README.md
atla_insights/client/client.py
atla_insights/client/types.py
atla_insights/client/.openapi-generator/FILES
atla_insights/client/.openapi-generator/VERSION
atla_insights/client/_generated_client/__init__.py
atla_insights/client/_generated_client/api_client.py
atla_insights/client/_generated_client/api_response.py
atla_insights/client/_generated_client/configuration.py
atla_insights/client/_generated_client/exceptions.py
atla_insights/client/_generated_client/rest.py
atla_insights/client/_generated_client/api/__init__.py
atla_insights/client/_generated_client/api/audio_api.py
atla_insights/client/_generated_client/api/sdk_api.py
atla_insights/client/_generated_client/docs/Annotation.md
atla_insights/client/_generated_client/docs/AudioApi.md
atla_insights/client/_generated_client/docs/CustomMetric.md
atla_insights/client/_generated_client/docs/CustomMetricValue.md
atla_insights/client/_generated_client/docs/DetailedTraceListResponse.md
atla_insights/client/_generated_client/docs/SDKApi.md
atla_insights/client/_generated_client/docs/Span.md
atla_insights/client/_generated_client/docs/Trace.md
atla_insights/client/_generated_client/docs/TraceDetailResponse.md
atla_insights/client/_generated_client/docs/TraceListResponse.md
atla_insights/client/_generated_client/docs/TraceWithDetails.md
atla_insights-0.0.40.dist-info/METADATA
atla_insights-0.0.40.dist-info/WHEEL
atla_insights-0.0.40.dist-info/licenses/LICENSE
atla_insights-0.0.40.dist-info/RECORD
