Metadata-Version: 2.4
Name: atla-insights
Version: 0.0.40
Summary: Atla is a platform for monitoring and improving AI agents.
Project-URL: Homepage, https://atla-ai.com
Author-email: Atla Team <support@atla-ai.com>
License: Apache-2.0
License-File: LICENSE
Classifier: License :: OSI Approved :: Apache Software License
Classifier: Programming Language :: Python :: 3
Classifier: Programming Language :: Python :: 3.10
Requires-Python: >=3.10
Requires-Dist: cuid2>=2.0.1
Requires-Dist: httpx>=0.24.0
Requires-Dist: human-id>=0.2.0
Requires-Dist: openai>=1.77.0
Requires-Dist: openinference-instrumentation>=0.1.32
Requires-Dist: openinference-semantic-conventions>=0.1.24
Requires-Dist: opentelemetry-api>=1.32.1
Requires-Dist: opentelemetry-exporter-otlp-proto-grpc>=1.32.1
Requires-Dist: opentelemetry-exporter-otlp-proto-http>=1.32.1
Requires-Dist: opentelemetry-instrumentation>=0.54b0
Requires-Dist: pydantic>=2.11.4
Requires-Dist: pygit2>=1.16.0
Requires-Dist: python-dateutil>=2.8.0
Requires-Dist: rich>=13.9.4
Requires-Dist: wrapt<2.0.0,>=1.17.2
Provides-Extra: agno
Requires-Dist: agno>=1.5.2; extra == 'agno'
Requires-Dist: openinference-instrumentation-agno>=0.1.15; extra == 'agno'
Provides-Extra: all
Requires-Dist: agno>=1.5.2; extra == 'all'
Requires-Dist: anthropic[bedrock]>=0.52.1; extra == 'all'
Requires-Dist: baml-py>=0.201.0; extra == 'all'
Requires-Dist: boto3>=1.38.17; extra == 'all'
Requires-Dist: claude-agent-sdk>=0.1.5; extra == 'all'
Requires-Dist: claude-code-sdk>=0.0.21; extra == 'all'
Requires-Dist: crewai>=0.130.0; extra == 'all'
Requires-Dist: elevenlabs>=2.16.0; extra == 'all'
Requires-Dist: google-adk>=1.2.1; extra == 'all'
Requires-Dist: google-genai>=1.19.0; extra == 'all'
Requires-Dist: google-generativeai>=0.7.0; extra == 'all'
Requires-Dist: langchain-openai>=0.3.4; extra == 'all'
Requires-Dist: langchain>=0.3.18; extra == 'all'
Requires-Dist: langgraph>=0.3.20; extra == 'all'
Requires-Dist: litellm<1.74.0,>=1.72.0; extra == 'all'
Requires-Dist: mcp>=1.9.0; extra == 'all'
Requires-Dist: openai-agents>=0.0.7; extra == 'all'
Requires-Dist: openinference-instrumentation-agno>=0.1.15; extra == 'all'
Requires-Dist: openinference-instrumentation-anthropic>=0.1.18; extra == 'all'
Requires-Dist: openinference-instrumentation-bedrock>=0.1.26; extra == 'all'
Requires-Dist: openinference-instrumentation-crewai==0.1.10; extra == 'all'
Requires-Dist: openinference-instrumentation-google-adk>=0.1.4; extra == 'all'
Requires-Dist: openinference-instrumentation-google-genai==0.1.2; extra == 'all'
Requires-Dist: openinference-instrumentation-langchain==0.1.43; extra == 'all'
Requires-Dist: openinference-instrumentation-mcp>=1.3.0; extra == 'all'
Requires-Dist: openinference-instrumentation-openai-agents>=1.3.0; extra == 'all'
Requires-Dist: openinference-instrumentation-openai>=0.1.30; extra == 'all'
Requires-Dist: openinference-instrumentation-pydantic-ai==0.1.8; extra == 'all'
Requires-Dist: openinference-instrumentation-smolagents==0.1.14; extra == 'all'
Requires-Dist: pydantic-ai>=0.2.0; extra == 'all'
Requires-Dist: smolagents<1.21.0,>=1.19.0; extra == 'all'
Provides-Extra: anthropic
Requires-Dist: anthropic[bedrock]>=0.52.1; extra == 'anthropic'
Requires-Dist: openinference-instrumentation-anthropic>=0.1.18; extra == 'anthropic'
Provides-Extra: baml
Requires-Dist: baml-py>=0.201.0; extra == 'baml'
Provides-Extra: bedrock
Requires-Dist: boto3>=1.38.17; extra == 'bedrock'
Requires-Dist: openinference-instrumentation-bedrock>=0.1.26; extra == 'bedrock'
Provides-Extra: ci
Requires-Dist: mypy>=1.15.0; extra == 'ci'
Requires-Dist: pytest-asyncio>=0.26.0; extra == 'ci'
Requires-Dist: pytest-httpserver>=1.1.3; extra == 'ci'
Requires-Dist: pytest>=8.3.4; extra == 'ci'
Requires-Dist: ruff>=0.11.7; extra == 'ci'
Provides-Extra: claude-agent-sdk
Requires-Dist: claude-agent-sdk>=0.1.5; extra == 'claude-agent-sdk'
Provides-Extra: claude-code-sdk
Requires-Dist: claude-code-sdk>=0.0.21; extra == 'claude-code-sdk'
Provides-Extra: crewai
Requires-Dist: crewai>=0.130.0; extra == 'crewai'
Requires-Dist: litellm<1.74.0,>=1.72.0; extra == 'crewai'
Requires-Dist: openinference-instrumentation-crewai==0.1.10; extra == 'crewai'
Provides-Extra: elevenlabs
Requires-Dist: elevenlabs>=2.16.0; extra == 'elevenlabs'
Provides-Extra: google-adk
Requires-Dist: google-adk>=1.2.1; extra == 'google-adk'
Requires-Dist: openinference-instrumentation-google-adk>=0.1.4; extra == 'google-adk'
Provides-Extra: google-genai
Requires-Dist: google-genai>=1.19.0; extra == 'google-genai'
Requires-Dist: openinference-instrumentation-google-genai==0.1.2; extra == 'google-genai'
Provides-Extra: google-generativeai
Requires-Dist: google-generativeai>=0.7.0; extra == 'google-generativeai'
Requires-Dist: openinference-instrumentation-google-genai==0.1.2; extra == 'google-generativeai'
Provides-Extra: langchain
Requires-Dist: langchain-openai>=0.3.4; extra == 'langchain'
Requires-Dist: langchain>=0.3.18; extra == 'langchain'
Requires-Dist: langgraph>=0.3.20; extra == 'langchain'
Requires-Dist: openinference-instrumentation-langchain==0.1.43; extra == 'langchain'
Provides-Extra: litellm
Requires-Dist: litellm<1.74.0,>=1.72.0; extra == 'litellm'
Provides-Extra: mcp
Requires-Dist: mcp>=1.9.0; extra == 'mcp'
Requires-Dist: openinference-instrumentation-mcp>=1.3.0; extra == 'mcp'
Provides-Extra: openai
Requires-Dist: openinference-instrumentation-openai>=0.1.30; extra == 'openai'
Provides-Extra: openai-agents
Requires-Dist: openai-agents>=0.0.7; extra == 'openai-agents'
Requires-Dist: openinference-instrumentation-openai-agents>=1.3.0; extra == 'openai-agents'
Requires-Dist: openinference-instrumentation-openai>=0.1.30; extra == 'openai-agents'
Provides-Extra: pydantic-ai
Requires-Dist: openinference-instrumentation-pydantic-ai==0.1.8; extra == 'pydantic-ai'
Requires-Dist: pydantic-ai>=0.2.0; extra == 'pydantic-ai'
Provides-Extra: smolagents
Requires-Dist: openinference-instrumentation-smolagents==0.1.14; extra == 'smolagents'
Requires-Dist: smolagents<1.21.0,>=1.19.0; extra == 'smolagents'
